{
    "name": "root",
    "metadata": {
        "timer_format_version": "0.1.0",
        "start_time_seconds": "1690071440",
        "python_version": "3.9.7 (tags/v3.9.7:1016ef3, Aug 30 2021, 20:19:38) [MSC v.1929 64 bit (AMD64)]",
        "command_line_arguments": "C:\\Users\\Ezra\\Gladiator\\venv\\Scripts\\mlagents-learn --run-id=MoveToOpponent --torch-device=cuda --resume",
        "mlagents_version": "0.30.0",
        "mlagents_envs_version": "0.30.0",
        "communication_protocol_version": "1.5.0",
        "pytorch_version": "2.0.1+cu117",
        "numpy_version": "1.21.2",
        "end_time_seconds": "1690071448"
    },
    "total": 7.9418449,
    "count": 1,
    "self": 0.004550200000000615,
    "children": {
        "run_training.setup": {
            "total": 0.01642049999999995,
            "count": 1,
            "self": 0.01642049999999995
        },
        "TrainerController.start_learning": {
            "total": 7.9208742,
            "count": 1,
            "self": 6.85000000011371e-05,
            "children": {
                "TrainerController._reset_env": {
                    "total": 7.354037999999999,
                    "count": 1,
                    "self": 7.354037999999999
                },
                "trainer_threads": {
                    "total": 3.9999999934536845e-07,
                    "count": 1,
                    "self": 3.9999999934536845e-07
                },
                "TrainerController._save_models": {
                    "total": 0.5667673000000004,
                    "count": 1,
                    "self": 0.0033263000000012255,
                    "children": {
                        "RLTrainer._checkpoint": {
                            "total": 0.5634409999999992,
                            "count": 1,
                            "self": 0.5634409999999992
                        }
                    }
                }
            }
        }
    }
}